ungraph/.env.example
ungraph/__init__.py
ungraph/application/__init__.py
ungraph/application/dependencies.py
ungraph/application/use_cases/__init__.py
ungraph/application/use_cases/ingest_document.py
ungraph/core/__init__.py
ungraph/core/configuration.py
ungraph/domain/__init__.py
ungraph/domain/entities/chunk.py
ungraph/domain/entities/document.py
ungraph/domain/entities/entity.py
ungraph/domain/entities/fact.py
ungraph/domain/entities/file.py
ungraph/domain/entities/page.py
ungraph/domain/entities/relation.py
ungraph/domain/repositories/chunk_repository.py
ungraph/domain/services/__init__.py
ungraph/domain/services/chunking_service.py
ungraph/domain/services/document_loader_service.py
ungraph/domain/services/embedding_service.py
ungraph/domain/services/index_service.py
ungraph/domain/services/inference_service.py
ungraph/domain/services/pattern_service.py
ungraph/domain/services/search_service.py
ungraph/domain/services/text_cleaning_service.py
ungraph/domain/value_objects/__init__.py
ungraph/domain/value_objects/document_type.py
ungraph/domain/value_objects/embedding.py
ungraph/domain/value_objects/graph_pattern.py
ungraph/domain/value_objects/predefined_patterns.py
ungraph/domain/value_objects/provenance.py
ungraph/infrastructure/__init__.py
ungraph/infrastructure/repositories/__init__.py
ungraph/infrastructure/repositories/neo4j_chunk_repository.py
ungraph/infrastructure/services/__init__.py
ungraph/infrastructure/services/advanced_search_patterns.py
ungraph/infrastructure/services/gds_service.py
ungraph/infrastructure/services/graphrag_search_patterns.py
ungraph/infrastructure/services/huggingface_embedding_service.py
ungraph/infrastructure/services/langchain_chunking_service.py
ungraph/infrastructure/services/langchain_document_loader_service.py
ungraph/infrastructure/services/llm_inference_service.py
ungraph/infrastructure/services/neo4j_index_service.py
ungraph/infrastructure/services/neo4j_pattern_service.py
ungraph-0.1.5.dist-info/METADATA
ungraph-0.1.5.dist-info/WHEEL
ungraph-0.1.5.dist-info/licenses/LICENSE
ungraph-0.1.5.dist-info/RECORD
