Metadata-Version: 2.4
Name: ungraph
Version: 0.1.5
Summary: Python framework for building Knowledge Graphs from unstructured text using Neo4j Cypher (property-graph query language), with alignment toward ISO GQL standards
Author-email: Alejandro Giraldo Londoño <alejandro@qnow.tech>
License: MIT
License-File: LICENSE
Keywords: knowledge-graph,langchain,neo4j,rag,unstructured-data
Classifier: Development Status :: 3 - Alpha
Classifier: Intended Audience :: Developers
Classifier: License :: OSI Approved :: MIT License
Classifier: Programming Language :: Python :: 3
Classifier: Programming Language :: Python :: 3.12
Requires-Python: >=3.12
Requires-Dist: chardet>=5.2.0
Requires-Dist: langchain-community>=0.4.1
Requires-Dist: langchain-docling>=2.0.0
Requires-Dist: langchain-experimental>=0.4.1
Requires-Dist: langchain-huggingface>=1.2.0
Requires-Dist: langchain-neo4j>=0.6.0
Requires-Dist: langchain-text-splitters>=1.1.0
Requires-Dist: langchain>=1.2.0
Requires-Dist: langgraph>=1.0.5
Requires-Dist: markdown>=3.10
Requires-Dist: neo4j>=5.28.2
Requires-Dist: pydantic-settings>=2.12.0
Requires-Dist: pydantic>=2.12.5
Requires-Dist: python-dotenv>=1.2.1
Requires-Dist: sentence-transformers>=5.2.0
Requires-Dist: unstructured>=0.18.21
Provides-Extra: all
Requires-Dist: graphdatascience>=1.18; extra == 'all'
Requires-Dist: matplotlib>=3.10.8; extra == 'all'
Requires-Dist: mypy>=1.19.1; extra == 'all'
Requires-Dist: opik>=1.9.66; extra == 'all'
Requires-Dist: pip>=25.3; extra == 'all'
Requires-Dist: ruff>=0.14.10; extra == 'all'
Requires-Dist: spacy>=3.8.11; extra == 'all'
Requires-Dist: yfiles-jupyter-graphs-for-neo4j>=1.7.0; extra == 'all'
Provides-Extra: dev
Requires-Dist: matplotlib>=3.10.8; extra == 'dev'
Requires-Dist: mypy>=1.19.1; extra == 'dev'
Requires-Dist: pip>=25.3; extra == 'dev'
Requires-Dist: ruff>=0.14.10; extra == 'dev'
Provides-Extra: experiments
Requires-Dist: opik>=1.9.66; extra == 'experiments'
Provides-Extra: gds
Requires-Dist: graphdatascience>=1.18; extra == 'gds'
Provides-Extra: infer
Requires-Dist: spacy>=3.8.11; extra == 'infer'
Provides-Extra: infer-all
Requires-Dist: spacy>=3.8.11; extra == 'infer-all'
Provides-Extra: infer-en
Requires-Dist: spacy>=3.8.11; extra == 'infer-en'
Provides-Extra: infer-es
Requires-Dist: spacy>=3.8.11; extra == 'infer-es'
Provides-Extra: ynet
Requires-Dist: yfiles-jupyter-graphs-for-neo4j>=1.7.0; extra == 'ynet'
